mplp/__init__.py
mplp_sdk-1.0.3.dist-info/METADATA
mplp_sdk-1.0.3.dist-info/WHEEL
mplp_sdk-1.0.3.dist-info/top_level.txt
mplp_sdk-1.0.3.dist-info/RECORD
