Metadata-Version: 2.4
Name: mplp-sdk
Version: 1.0.3
Summary: Python SDK and reference runtime for the MPLP Protocol (Agent OS Protocol).
Author: Coregentis AI
License: Apache-2.0
Project-URL: Homepage, https://mplp.io
Project-URL: Documentation, https://docs.mplp.io
Project-URL: Repository, https://github.com/Coregentis/MPLP-Protocol
Project-URL: Issues, https://github.com/Coregentis/MPLP-Protocol/issues
Keywords: mplp,multi-agent,lifecycle,protocol,agent-os,AI agents,runtime
Classifier: Development Status :: 5 - Production/Stable
Classifier: Intended Audience :: Developers
Classifier: License :: OSI Approved :: Apache Software License
Classifier: Programming Language :: Python :: 3
Classifier: Programming Language :: Python :: 3.10
Classifier: Programming Language :: Python :: 3.11
Classifier: Programming Language :: Python :: 3.12
Classifier: Topic :: Software Development :: Libraries
Classifier: Topic :: Software Development :: Libraries :: Application Frameworks
Classifier: Typing :: Typed
Requires-Python: >=3.10
Requires-Dist: pydantic<3.0,>=2.0
